LICENSE.txt
MANIFEST.in
README.rst
setup.cfg
setup.py
compact_distillation.egg-info/PKG-INFO
compact_distillation.egg-info/SOURCES.txt
compact_distillation.egg-info/dependency_links.txt
compact_distillation.egg-info/requires.txt
compact_distillation.egg-info/top_level.txt
distillation/__init__.py
distillation/semiSupervised.py
distillation/utils.py